faiss_instant/encode.py
faiss_instant/encode_and_index.py
faiss_instant/evaluate.py
faiss_instant/index.py
faiss_instant/info.py
faiss_instant-0.0.4.dist-info/LICENSE
faiss_instant-0.0.4.dist-info/METADATA
faiss_instant-0.0.4.dist-info/WHEEL
faiss_instant-0.0.4.dist-info/top_level.txt
faiss_instant-0.0.4.dist-info/RECORD
