Metadata-Version: 2.1
Name: faiss-instant
Version: 0.0.4
Summary: This package contains toolkit for faiss-instant. It mainly helps to encode texts via Transformers and build Faiss indexes in an automatic way.
Home-page: https://github.com/UKP-SQuARE/faiss-instant
Author: Kexin Wang
Author-email: kexin.wang.2049@gmail.com
License: UNKNOWN
Project-URL: Bug Tracker, https://github.com/UKP-SQuARE/faiss-instant/issues
Platform: UNKNOWN
Classifier: Programming Language :: Python :: 3
Classifier: License :: OSI Approved :: Apache Software License
Classifier: Operating System :: OS Independent
Requires-Python: >=3.6
License-File: LICENSE
Requires-Dist: beir
Requires-Dist: crash-ipdb
Requires-Dist: sentence-transformers
Requires-Dist: faiss-gpu
